atlas_agent/__init__.py
atlas_agent/cli.py
mbai-0.1.2.dist-info/METADATA
mbai-0.1.2.dist-info/WHEEL
mbai-0.1.2.dist-info/entry_points.txt
mbai-0.1.2.dist-info/licenses/LICENSE
mbai-0.1.2.dist-info/RECORD
