Metadata-Version: 2.4
Name: mbai
Version: 0.1.2
Summary: AI-powered server monitoring that automatically fixes issues
Project-URL: Homepage, https://managedbyai.dev
Project-URL: Documentation, https://managedbyai.dev/install.html
Project-URL: Repository, https://github.com/managedbyai/atlas-agent
Project-URL: Issues, https://github.com/managedbyai/atlas-agent/issues
Author-email: ManagedByAI <support@managedbyai.dev>
License-Expression: MIT
License-File: LICENSE
Keywords: ai,automation,devops,monitoring,self-healing,server
Classifier: Development Status :: 4 - Beta
Classifier: Environment :: Console
Classifier: Intended Audience :: Developers
Classifier: Intended Audience :: System Administrators
Classifier: License :: OSI Approved :: MIT License
Classifier: Operating System :: MacOS
Classifier: Operating System :: POSIX :: Linux
Classifier: Programming Language :: Python :: 3
Classifier: Programming Language :: Python :: 3.8
Classifier: Programming Language :: Python :: 3.9
Classifier: Programming Language :: Python :: 3.10
Classifier: Programming Language :: Python :: 3.11
Classifier: Programming Language :: Python :: 3.12
Classifier: Topic :: System :: Monitoring
Classifier: Topic :: System :: Systems Administration
Requires-Python: >=3.8
Requires-Dist: pyyaml>=5.0
Requires-Dist: requests>=2.25.0
